erniebotchat/__init__.py
erniebotchat/erniebot.py
erniebotchat/error/__init__.py
erniebotchat/error/customerror.py
erniebotchat/service/__init__.py
erniebotchat/service/explain.py
erniebotchat/util/__init__.py
erniebotchat/util/httputils.py
erniechatbotsdk-0.0.13.dist-info/LICENSE
erniechatbotsdk-0.0.13.dist-info/METADATA
erniechatbotsdk-0.0.13.dist-info/WHEEL
erniechatbotsdk-0.0.13.dist-info/top_level.txt
erniechatbotsdk-0.0.13.dist-info/RECORD
